cal_mkdocs/__init__.py
cal_mkdocs/__main__.py
cal_mkdocs/add_xref.py
cal_mkdocs/main.py
cal_mkdocs/version.py
cal_mkdocs/themes/__init__.py
cal_mkdocs/themes/theme_cal/__init__.py
cal_mkdocs/themes/theme_cal/cal-theme.yml
cal_mkdocs/themes/theme_cal/extra.css
cal_mkdocs/themes/theme_cal/iframe-worker.js
cal_mkdocs/themes/theme_cal/.icons/__init__.py
cal_mkdocs/themes/theme_cal/.icons/logo.svg
cal_mkdocs/themes/theme_cal/.icons/moon.svg
cal_mkdocs/themes/theme_cal/.icons/sun.svg
cal_mkdocs/themes/theme_cal/partials/__init__.py
cal_mkdocs/themes/theme_cal/partials/header.html
cal_mkdocs/themes/theme_std/__init__.py
cal_mkdocs/themes/theme_std/iframe-worker.js
cal_mkdocs/themes/theme_std/std-theme.yml
cal_mkdocs/themes/theme_std/.icons/__init__.py
cal_mkdocs/themes/theme_std/.icons/blanklogo.svg
cal_mkdocs/themes/theme_std/partials/__init__.py
cal_mkdocs/themes/theme_std/partials/header.html
cal_mkdocs-1.0.0.dist-info/METADATA
cal_mkdocs-1.0.0.dist-info/WHEEL
cal_mkdocs-1.0.0.dist-info/entry_points.txt
cal_mkdocs-1.0.0.dist-info/RECORD
