Metadata-Version: 2.4
Name: cal-mkdocs
Version: 1.0.0
Requires-Python: >=3.12
Requires-Dist: mkdocs
Requires-Dist: mkdocs-material
Requires-Dist: mkdocstrings-python
Requires-Dist: pymdown-extensions
